starttf/__init__.py
starttf/cluster/__init__.py
starttf/cluster/client.py
starttf/cluster/gpu_checker.py
starttf/cluster/helpers.py
starttf/cluster/server.py
starttf/data/__init__.py
starttf/data/autoqueue.py
starttf/data/autorecords.py
starttf/estimators/__init__.py
starttf/estimators/keras_trainer.py
starttf/estimators/tf_estimator.py
starttf/layers/__init__.py
starttf/layers/caffe_tensorflow.py
starttf/layers/tile_2d.py
starttf/losses/__init__.py
starttf/losses/basic_losses.py
starttf/losses/loss_processors.py
starttf/losses/utils.py
starttf/models/__init__.py
starttf/models/encoders.py
starttf/models/model.py
starttf/models/tf_hub_wrapper.py
starttf/rl/__init__.py
starttf/rl/agents/__init__.py
starttf/rl/agents/agent.py
starttf/utils/__init__.py
starttf/utils/create_optimizer.py
starttf/utils/hyperparams.py
starttf/utils/image_manipulation.py
starttf/utils/imagenet_classes.py
starttf/utils/misc.py
starttf/utils/model_io.py
starttf/utils/plot_losses.py
starttf/utils/session_config.py
starttf/utils/universal_keras_wrapper.py
starttf-1.0.3.dist-info/LICENSE
starttf-1.0.3.dist-info/METADATA
starttf-1.0.3.dist-info/WHEEL
starttf-1.0.3.dist-info/top_level.txt
starttf-1.0.3.dist-info/RECORD
