Metadata-Version: 2.1
Name: starttf
Version: 1.0.3
Summary: A tensorflow batteries included kit to write tensorflow networks from scratch or use existing ones.
Home-page: https://github.com/penguinmenac3/starttf
Author: Michael Fuerst
Author-email: mail@michaelfuerst.de
License: BSD
Download-URL: https://github.com/penguinmenac3/starttf/tarball/1.0.3
Platform: UNKNOWN
Classifier: Development Status :: 3 - Alpha
Classifier: Intended Audience :: Developers
Classifier: Programming Language :: Python
Requires-Dist: numpy
Requires-Dist: scikit-image
Requires-Dist: scikit-learn
Requires-Dist: scipy
Requires-Dist: matplotlib
Requires-Dist: h5py
Requires-Dist: pandas
Requires-Dist: opencv-python
Requires-Dist: tensorflow-hub
Requires-Dist: hyperparams
Requires-Dist: opendatalake
Requires-Dist: GPUtil
Requires-Dist: keras
